mlmicrophysics/__init__.py
mlmicrophysics/data.py
mlmicrophysics/data_test.py
mlmicrophysics/explain.py
mlmicrophysics/explain_test.py
mlmicrophysics/metrics.py
mlmicrophysics/models.py
mlmicrophysics/models_test.py
mlmicrophysics/output_dnn_nc.py
mlmicrophysics/plots.py
mlmicrophysics/plots_test.py
mlmicrophysics-0.1.1.dist-info/LICENSE
mlmicrophysics-0.1.1.dist-info/METADATA
mlmicrophysics-0.1.1.dist-info/WHEEL
mlmicrophysics-0.1.1.dist-info/top_level.txt
mlmicrophysics-0.1.1.dist-info/RECORD
