Metadata-Version: 2.1
Name: mlmicrophysics
Version: 0.1.1
Summary: Machine learning emulator testbed for microphysics.
Home-page: https://github.com/NCAR/mlmicrophysics
Author: David John Gagne and Gabrielle Gantos
Author-email: dgagne@ucar.edu
License: MIT
Platform: UNKNOWN
Requires-Dist: numpy
Requires-Dist: scipy
Requires-Dist: pandas
Requires-Dist: matplotlib
Requires-Dist: xarray
Requires-Dist: tensorflow
Requires-Dist: netcdf4
Requires-Dist: scikit-learn
Requires-Dist: pyyaml
Requires-Dist: pyarrow
